{
  "Version": 1,
  "SaveTime": "2025-12-21T11:22:34.4085113+07:00",
  "SlotName": "Slot 1",
  "Player": {
    "PositionX": 320,
    "PositionY": 64,
    "CurrentHealth": 90,
    "Level": 1,
    "CurrentXP": 50,
    "Gold": 100,
    "MutationPoints": 4,
    "FreeMutationPicks": 0,
    "PendingAttributePoints": 0,
    "ReservedAP": 1,
    "CurrentEsperPoints": 2,
    "SciencePath": 0,
    "Attributes": {
      "STR": 6,
      "AGI": 6,
      "END": 5,
      "INT": 4,
      "PER": 5,
      "WIL": 4
    },
    "BodyParts": [
      {
        "Id": "Head",
        "Type": 0,
        "Name": "Head",
        "CurrentHealth": 75,
        "MaxHealth": 75,
        "IsMutationPart": false,
        "Injuries": [],
        "Ailments": []
      },
      {
        "Id": "Brain",
        "Type": 1,
        "Name": "Brain",
        "CurrentHealth": 50,
        "MaxHealth": 50,
        "IsMutationPart": false,
        "ParentId": "Head",
        "Injuries": [],
        "Ailments": []
      },
      {
        "Id": "LeftEye",
        "Type": 2,
        "Name": "Left Eye",
        "CurrentHealth": 25,
        "MaxHealth": 25,
        "IsMutationPart": false,
        "ParentId": "Head",
        "Injuries": [],
        "Ailments": []
      },
      {
        "Id": "RightEye",
        "Type": 3,
        "Name": "Right Eye",
        "CurrentHealth": 25,
        "MaxHealth": 25,
        "IsMutationPart": false,
        "ParentId": "Head",
        "Injuries": [],
        "Ailments": []
      },
      {
        "Id": "Nose",
        "Type": 4,
        "Name": "Nose",
        "CurrentHealth": 20,
        "MaxHealth": 20,
        "IsMutationPart": false,
        "ParentId": "Head",
        "Injuries": [],
        "Ailments": []
      },
      {
        "Id": "Jaw",
        "Type": 5,
        "Name": "Jaw",
        "CurrentHealth": 40,
        "MaxHealth": 40,
        "IsMutationPart": false,
        "ParentId": "Head",
        "Injuries": [],
        "Ailments": []
      },
      {
        "Id": "Torso",
        "Type": 6,
        "Name": "Torso",
        "CurrentHealth": 150,
        "MaxHealth": 150,
        "IsMutationPart": false,
        "Injuries": [],
        "Ailments": []
      },
      {
        "Id": "Heart",
        "Type": 7,
        "Name": "Heart",
        "CurrentHealth": 50,
        "MaxHealth": 50,
        "IsMutationPart": false,
        "ParentId": "Torso",
        "Injuries": [],
        "Ailments": []
      },
      {
        "Id": "LeftLung",
        "Type": 8,
        "Name": "Left Lung",
        "CurrentHealth": 40,
        "MaxHealth": 40,
        "IsMutationPart": false,
        "ParentId": "Torso",
        "Injuries": [],
        "Ailments": []
      },
      {
        "Id": "RightLung",
        "Type": 9,
        "Name": "Right Lung",
        "CurrentHealth": 40,
        "MaxHealth": 40,
        "IsMutationPart": false,
        "ParentId": "Torso",
        "Injuries": [],
        "Ailments": []
      },
      {
        "Id": "Stomach",
        "Type": 10,
        "Name": "Stomach",
        "CurrentHealth": 45,
        "MaxHealth": 45,
        "IsMutationPart": false,
        "ParentId": "Torso",
        "Injuries": [],
        "Ailments": []
      },
      {
        "Id": "Liver",
        "Type": 11,
        "Name": "Liver",
        "CurrentHealth": 45,
        "MaxHealth": 45,
        "IsMutationPart": false,
        "ParentId": "Torso",
        "Injuries": [],
        "Ailments": []
      },
      {
        "Id": "LeftArm",
        "Type": 12,
        "Name": "Left Arm",
        "CurrentHealth": 60,
        "MaxHealth": 60,
        "IsMutationPart": false,
        "ParentId": "Torso",
        "Injuries": [],
        "Ailments": []
      },
      {
        "Id": "LeftHand",
        "Type": 14,
        "Name": "Left Hand",
        "CurrentHealth": 35,
        "MaxHealth": 35,
        "IsMutationPart": false,
        "ParentId": "LeftArm",
        "Injuries": [],
        "Ailments": []
      },
      {
        "Id": "RightArm",
        "Type": 13,
        "Name": "Right Arm",
        "CurrentHealth": 60,
        "MaxHealth": 60,
        "IsMutationPart": false,
        "ParentId": "Torso",
        "Injuries": [],
        "Ailments": []
      },
      {
        "Id": "RightHand",
        "Type": 15,
        "Name": "Right Hand",
        "CurrentHealth": 35,
        "MaxHealth": 35,
        "IsMutationPart": false,
        "ParentId": "RightArm",
        "Injuries": [],
        "Ailments": []
      },
      {
        "Id": "LeftLeg",
        "Type": 16,
        "Name": "Left Leg",
        "CurrentHealth": 70,
        "MaxHealth": 70,
        "IsMutationPart": false,
        "ParentId": "Torso",
        "Injuries": [],
        "Ailments": []
      },
      {
        "Id": "LeftFoot",
        "Type": 18,
        "Name": "Left Foot",
        "CurrentHealth": 35,
        "MaxHealth": 35,
        "IsMutationPart": false,
        "ParentId": "LeftLeg",
        "Injuries": [],
        "Ailments": []
      },
      {
        "Id": "RightLeg",
        "Type": 17,
        "Name": "Right Leg",
        "CurrentHealth": 70,
        "MaxHealth": 70,
        "IsMutationPart": false,
        "ParentId": "Torso",
        "Injuries": [],
        "Ailments": []
      },
      {
        "Id": "RightFoot",
        "Type": 19,
        "Name": "Right Foot",
        "CurrentHealth": 35,
        "MaxHealth": 35,
        "IsMutationPart": false,
        "ParentId": "RightLeg",
        "Injuries": [],
        "Ailments": []
      }
    ],
    "Mutations": [],
    "Traits": [
      40,
      19,
      6,
      20
    ],
    "Inventory": {
      "Items": [
        {
          "ItemDefId": "food_jerky",
          "StackCount": 5,
          "Durability": 100,
          "Quality": 2
        },
        {
          "ItemDefId": "water_dirty",
          "StackCount": 3,
          "Durability": 100,
          "Quality": 2
        },
        {
          "ItemDefId": "bandage",
          "StackCount": 2,
          "Durability": 100,
          "Quality": 2
        },
        {
          "ItemDefId": "stimpack",
          "StackCount": 1,
          "Durability": 100,
          "Quality": 2
        },
        {
          "ItemDefId": "void_essence",
          "StackCount": 2,
          "Durability": 100,
          "Quality": 2
        },
        {
          "ItemDefId": "knife_rusty",
          "StackCount": 1,
          "Durability": 100,
          "Quality": 2
        }
      ]
    },
    "Survival": {
      "Hunger": 94.72397,
      "Thirst": 93.50528,
      "Rest": 97.56634,
      "Temperature": 46.746384
    }
  },
  "Time": {
    "TimeOfDay": 8,
    "DayNumber": 1,
    "CurrentSeason": 0
  },
  "Enemies": [
    {
      "Id": "Raider_1",
      "Type": 0,
      "PositionX": 1950.0524,
      "PositionY": 673.94806,
      "CurrentHealth": 50,
      "MaxHealth": 50,
      "IsProvoked": false
    },
    {
      "Id": "Raider_2",
      "Type": 0,
      "PositionX": 2176,
      "PositionY": 1664,
      "CurrentHealth": 50,
      "MaxHealth": 50,
      "IsProvoked": false
    },
    {
      "Id": "Raider_3",
      "Type": 0,
      "PositionX": 1984,
      "PositionY": 3008,
      "CurrentHealth": 50,
      "MaxHealth": 50,
      "IsProvoked": false
    },
    {
      "Id": "Scavenger_4",
      "Type": 10,
      "PositionX": 1088,
      "PositionY": 2880,
      "CurrentHealth": 15,
      "MaxHealth": 15,
      "IsProvoked": false
    },
    {
      "Id": "WildBoar_5",
      "Type": 12,
      "PositionX": 832,
      "PositionY": 768,
      "CurrentHealth": 45,
      "MaxHealth": 45,
      "IsProvoked": false
    }
  ],
  "GroundItems": [],
  "Quests": {
    "ActiveQuests": [],
    "CompletedQuestIds": []
  },
  "World": {
    "CurrentZoneId": "start",
    "Structures": []
  },
  "PlayerLevel": 1
}